[
    {
        "audio-begin": 13918,
        "audio-end": 14437,
        "audio-file": "第24课-1.mp3",
        "chinese": "穿",
        "cid": 1609453876713,
        "guid": "O96fAv/CQk",
        "meaning": "put on; wear",
        "nid": 1609453876714,
        "part-of-speech": "verb",
        "pinyin": "chuān",
        "tags": " chinese-in-steps-3 lesson-24 "
    },
    {
        "audio-begin": 16650,
        "audio-end": 17115,
        "audio-file": "第24课-1.mp3",
        "chinese": "试",
        "cid": 1609453876715,
        "guid": "j3OEwA9WTz",
        "meaning": "try",
        "nid": 1609453876716,
        "part-of-speech": "verb",
        "pinyin": "shì",
        "tags": " chinese-in-steps-3 lesson-24 "
    },
    {
        "audio-begin": 19242,
        "audio-end": 20031,
        "audio-file": "第24课-1.mp3",
        "chinese": "适合",
        "cid": 1609453876717,
        "guid": "tr+6ObDIRJ",
        "meaning": "suit, fit",
        "nid": 1609453876718,
        "part-of-speech": "verb",
        "pinyin": "shìhé",
        "tags": " chinese-in-steps-3 lesson-24 "
    },
    {
        "audio-begin": 22217,
        "audio-end": 22959,
        "audio-file": "第24课-1.mp3",
        "chinese": "皮鞋",
        "cid": 1609453876719,
        "guid": "NYvWXJ+YRl",
        "meaning": "leather shoe",
        "nid": 1609453876720,
        "part-of-speech": "noun",
        "pinyin": "píxié",
        "tags": " chinese-in-steps-3 lesson-24 "
    },
    {
        "audio-begin": 25103,
        "audio-end": 25892,
        "audio-file": "第24课-1.mp3",
        "chinese": "场合",
        "cid": 1609453876721,
        "guid": "+33U2tAoTV",
        "meaning": "occasion",
        "nid": 1609453876722,
        "part-of-speech": "noun",
        "pinyin": "chǎnghé",
        "tags": " chinese-in-steps-3 lesson-24 "
    },
    {
        "audio-begin": 28015,
        "audio-end": 28799,
        "audio-file": "第24课-1.mp3",
        "chinese": "旗袍",
        "cid": 1609453876723,
        "guid": "o1dV9QrrRI",
        "meaning": "cheongsam",
        "nid": 1609453876724,
        "part-of-speech": "noun",
        "pinyin": "qípáo",
        "tags": " chinese-in-steps-3 lesson-24 "
    },
    {
        "audio-begin": 30937,
        "audio-end": 31680,
        "audio-file": "第24课-1.mp3",
        "chinese": "上衣",
        "cid": 1609453876725,
        "guid": "fm9SdMVWQw",
        "meaning": "upper outer garment",
        "nid": 1609453876726,
        "part-of-speech": "noun",
        "pinyin": "shàngyī",
        "tags": " chinese-in-steps-3 lesson-24 "
    },
    {
        "audio-begin": 33861,
        "audio-end": 34569,
        "audio-file": "第24课-1.mp3",
        "chinese": "颜色",
        "cid": 1609453876727,
        "guid": "lJMLFH45Rl",
        "meaning": "colour",
        "nid": 1609453876728,
        "part-of-speech": "noun",
        "pinyin": "yánsè",
        "tags": " chinese-in-steps-3 lesson-24 "
    },
    {
        "audio-begin": 36849,
        "audio-end": 37603,
        "audio-file": "第24课-1.mp3",
        "chinese": "款式",
        "cid": 1609453876729,
        "guid": "C51TdvdrRN",
        "meaning": "style",
        "nid": 1609453876730,
        "part-of-speech": "noun",
        "pinyin": "kuǎnshì",
        "tags": " chinese-in-steps-3 lesson-24 "
    },
    {
        "audio-begin": 39828,
        "audio-end": 40864,
        "audio-file": "第24课-1.mp3",
        "chinese": "试衣间",
        "cid": 1609453876731,
        "guid": "JQQuICIrRA",
        "meaning": "fitting room",
        "nid": 1609453876732,
        "part-of-speech": "noun",
        "pinyin": "shìyījiān",
        "tags": " chinese-in-steps-3 lesson-24 "
    },
    {
        "audio-begin": 45574,
        "audio-end": 46352,
        "audio-file": "第24课-1.mp3",
        "chinese": "大小",
        "cid": 1609453876733,
        "guid": "NookR22BTZ",
        "meaning": "size",
        "nid": 1609453876734,
        "part-of-speech": "noun",
        "pinyin": "dàxiǎo",
        "tags": " chinese-in-steps-3 lesson-24 "
    },
    {
        "audio-begin": 48576,
        "audio-end": 49331,
        "audio-file": "第24课-1.mp3",
        "chinese": "合适",
        "cid": 1609453876735,
        "guid": "owkA4IVeTh",
        "meaning": "suitable",
        "nid": 1609453876736,
        "part-of-speech": "adjective",
        "pinyin": "héshì",
        "tags": " chinese-in-steps-3 lesson-24 "
    },
    {
        "audio-begin": 51550,
        "audio-end": 52348,
        "audio-file": "第24课-1.mp3",
        "chinese": "鲜艳",
        "cid": 1609453876737,
        "guid": "QcA/mz/8Qn",
        "meaning": "brightly coloured",
        "nid": 1609453876738,
        "part-of-speech": "adjective",
        "pinyin": "xiānyàn",
        "tags": " chinese-in-steps-3 lesson-24 "
    },
    {
        "audio-begin": 54565,
        "audio-end": 55376,
        "audio-file": "第24课-1.mp3",
        "chinese": "流行",
        "cid": 1609453876739,
        "guid": "yYmHBs2HRt",
        "meaning": "popular",
        "nid": 1609453876740,
        "part-of-speech": "adjective",
        "pinyin": "liúxíng",
        "tags": " chinese-in-steps-3 lesson-24 "
    },
    {
        "audio-begin": 60126,
        "audio-end": 60808,
        "audio-file": "第24课-1.mp3",
        "chinese": "老气",
        "cid": 1609453876741,
        "guid": "l7aH1tGCSl",
        "meaning": "of old style and dark colour",
        "nid": 1609453876742,
        "part-of-speech": "adjective",
        "pinyin": "lǎoqì",
        "tags": " chinese-in-steps-3 lesson-24 "
    },
    {
        "audio-begin": 62963,
        "audio-end": 63710,
        "audio-file": "第24课-1.mp3",
        "chinese": "土气",
        "cid": 1609453876743,
        "guid": "mQofgiWkT9",
        "meaning": "rustic, unrefined",
        "nid": 1609453876744,
        "part-of-speech": "adjective",
        "pinyin": "tǔqì",
        "tags": " chinese-in-steps-3 lesson-24 "
    },
    {
        "audio-begin": 65925,
        "audio-end": 66573,
        "audio-file": "第24课-1.mp3",
        "chinese": "高贵",
        "cid": 1609453876745,
        "guid": "kPIrtA7pSw",
        "meaning": "noble, elegant",
        "nid": 1609453876746,
        "part-of-speech": "adjective",
        "pinyin": "gāoguì",
        "tags": " chinese-in-steps-3 lesson-24 "
    },
    {
        "audio-begin": 68850,
        "audio-end": 69341,
        "audio-file": "第24课-1.mp3",
        "chinese": "黑",
        "cid": 1609453876747,
        "guid": "0ZdSmfC7Rq",
        "meaning": "black",
        "nid": 1609453876748,
        "part-of-speech": "adjective",
        "pinyin": "hēi",
        "tags": " chinese-in-steps-3 lesson-24 "
    },
    {
        "audio-begin": 71664,
        "audio-end": 72128,
        "audio-file": "第24课-1.mp3",
        "chinese": "灰",
        "cid": 1609453876749,
        "guid": "1Eq5F1YFTi",
        "meaning": "grey",
        "nid": 1609453876750,
        "part-of-speech": "adjective",
        "pinyin": "huī",
        "tags": " chinese-in-steps-3 lesson-24 "
    },
    {
        "audio-begin": 74285,
        "audio-end": 74749,
        "audio-file": "第24课-1.mp3",
        "chinese": "蓝",
        "cid": 1609453876751,
        "guid": "1MQIfqB4R7",
        "meaning": "blue",
        "nid": 1609453876752,
        "part-of-speech": "adjective",
        "pinyin": "lán",
        "tags": " chinese-in-steps-3 lesson-24 "
    },
    {
        "audio-begin": 76872,
        "audio-end": 77385,
        "audio-file": "第24课-1.mp3",
        "chinese": "紫",
        "cid": 1609453876753,
        "guid": "WzdG/g3+Qo",
        "meaning": "purple",
        "nid": 1609453876754,
        "part-of-speech": "adjective",
        "pinyin": "zǐ",
        "tags": " chinese-in-steps-3 lesson-24 "
    },
    {
        "audio-begin": 79523,
        "audio-end": 80174,
        "audio-file": "第24课-1.mp3",
        "chinese": "正式",
        "cid": 1609453876755,
        "guid": "XsuQM4QDQE",
        "meaning": "formal",
        "nid": 1609453876756,
        "part-of-speech": "adjective",
        "pinyin": "zhèngshì",
        "tags": " chinese-in-steps-3 lesson-24 "
    },
    {
        "audio-begin": 82306,
        "audio-end": 83075,
        "audio-file": "第24课-1.mp3",
        "chinese": "可能",
        "cid": 1609453876757,
        "guid": "6+jTjBcASf",
        "meaning": "perhaps, maybe",
        "nid": 1609453876758,
        "part-of-speech": "adverb",
        "pinyin": "kěnéng",
        "tags": " chinese-in-steps-3 lesson-24 "
    },
    {
        "audio-begin": 85266,
        "audio-end": 86024,
        "audio-file": "第24课-1.mp3",
        "chinese": "正好",
        "cid": 1609453876759,
        "guid": "fyw/ZHHPTp",
        "meaning": "just right",
        "nid": 1609453876760,
        "part-of-speech": "adverb",
        "pinyin": "zhènghǎo",
        "tags": " chinese-in-steps-3 lesson-24 "
    },
    {
        "audio-begin": 88253,
        "audio-end": 88780,
        "audio-file": "第24课-1.mp3",
        "chinese": "双",
        "cid": 1609453876761,
        "guid": "zT/aOi+RQ1",
        "meaning": "a pair of (for footwear etc.)",
        "nid": 1609453876762,
        "part-of-speech": "measure word",
        "pinyin": "shuāng",
        "tags": " chinese-in-steps-3 lesson-24 "
    },
    {
        "audio-begin": 90973,
        "audio-end": 91332,
        "audio-file": "第24课-1.mp3",
        "chinese": "件",
        "cid": 1609453876763,
        "guid": "4qUkoiC7Tq",
        "meaning": "a piece of (for upper body clothing and matter etc.)",
        "nid": 1609453876764,
        "part-of-speech": "measure word",
        "pinyin": "jiàn",
        "tags": " chinese-in-steps-3 lesson-24 "
    }
]
